epdif/__init__.py
epdif-0.1.1.dist-info/LICENSE
epdif-0.1.1.dist-info/METADATA
epdif-0.1.1.dist-info/WHEEL
epdif-0.1.1.dist-info/top_level.txt
epdif-0.1.1.dist-info/RECORD
