Metadata-Version: 2.1
Name: epdif
Version: 0.1.1
Summary: EPD hardware interface implements (GPIO, SPI)
Home-page: https://github.com/t4skforce/epdif
Author: Yehui from Waveshare
Author-email: service@waveshare.com
License: GPL
Platform: UNKNOWN
Classifier: Programming Language :: Python
Classifier: Programming Language :: Python :: 3
Requires-Dist: spidev
Requires-Dist: RPi.GPIO
